{"cameraMode":{"drawMode":0,"name":"Shaded","section":"Shading Mode"},"sceneLighting":true,"audioPlay":false,"sceneViewState":{"m_AlwaysRefresh":false,"showFog":true,"showSkybox":true,"showFlares":true,"showImageEffects":true,"showParticleSystems":true,"showVisualEffectGraphs":true,"m_FxEnabled":true},"in2DMode":false,"pivot":{"x":31.76422882080078,"y":-28.384244918823243,"z":-45.78148651123047},"rotation":{"x":0.08916758745908737,"y":0.9090420007705689,"z":-0.31626415252685549,"w":0.256285697221756},"size":29.129562377929689,"orthographic":false}