{"cameraMode":{"drawMode":0,"name":"Shaded","section":"Shading Mode"},"sceneLighting":true,"audioPlay":false,"sceneViewState":{"m_AlwaysRefresh":false,"showFog":true,"showSkybox":true,"showFlares":true,"showImageEffects":true,"showParticleSystems":true,"showVisualEffectGraphs":true,"m_FxEnabled":true},"in2DMode":false,"pivot":{"x":-79.30689239501953,"y":-24.160924911499025,"z":-4.531260013580322},"rotation":{"x":0.18283097445964814,"y":-0.7103143334388733,"z":0.20019394159317017,"w":0.6498662829399109},"size":29.455692291259767,"orthographic":false}